README.md
setup.py
gpayments/__init__.py
gpayments/api_requestor.py
gpayments/error.py
gpayments/gpayments_object.py
gpayments/gpayments_response.py
gpayments/http_client.py
gpayments/multipart_data_generator.py
gpayments/oauth.py
gpayments/oauth_error.py
gpayments/resource.py
gpayments/six.py
gpayments/util.py
gpayments/version.py
gpayments/webhook.py
gpayments.egg-info/PKG-INFO
gpayments.egg-info/SOURCES.txt
gpayments.egg-info/dependency_links.txt
gpayments.egg-info/not-zip-safe
gpayments.egg-info/requires.txt
gpayments.egg-info/top_level.txt
gpayments/api_resources/__init__.py
gpayments/api_resources/account.py
gpayments/api_resources/charge.py
gpayments/api_resources/customer.py
gpayments/api_resources/list_object.py
gpayments/api_resources/plan.py
gpayments/api_resources/refund.py
gpayments/api_resources/simplecharge.py
gpayments/api_resources/subscription.py
gpayments/api_resources/abstract/__init__.py
gpayments/api_resources/abstract/api_resource.py
gpayments/api_resources/abstract/createable_api_resource.py
gpayments/api_resources/abstract/deletable_api_resource.py
gpayments/api_resources/abstract/listable_api_resource.py
gpayments/api_resources/abstract/nested_resource_class_methods.py
gpayments/api_resources/abstract/singleton_api_resource.py
gpayments/api_resources/abstract/updateable_api_resource.py
gpayments/api_resources/abstract/verify_mixin.py
gpayments/data/ca-certificates.crt