Metadata-Version: 1.1
Name: gpayments
Version: 0.2
Summary: Client for 4Geeks Payments
Home-page: https://github.com/4GeeksDev/gpayments-python
Author: 4Geeks Technologies, Inc
Author-email: hello@4geeks.io
License: MIT
Download-URL: https://github.com/4GeeksDev/gpayments-python/tarball/master
Keywords: 4geeks payments
Platform: UNKNOWN
